
[{"content":"Hi @everyone!\nThis is the first article here.\nMight as well introduce myself!\nI am Lia Milenakos - a transfem lesbian catgirl who goes by she/her.\nI\u0026rsquo;m mostly known for my Cat Bot as well as my Cell Machine adventures.\nWhat is Cat Bot? # Cat Bot is a Discord bot I have been working on for the past two years. The core concept is the following:\nCats spawn in a specific channel First to catch the cat gets it Collect many cats Get into the leaderboards Collect achievements Have fun All data is separate between servers creating an equal and fun experience.\nI\u0026rsquo;m sure this won\u0026rsquo;t be my last time mentioning Cat Bot and you most likely already know what it is.\nWhat is Cell Machine? # Cell Machine was originally a game developed by Sam Hogan in 48 hours for a game jam, consisting of 17 levels. Many people quickly fell in love with this celluar automata and wanted a sandbox mode, which is how first Cell Machine mods were created.\nThe most popular Cell Machine game at the moment is Cell Machine Mystic Mod, or CMMM for short. I myself have created many modifications of CMMM and a few other Cell Machines, which you can find on my itch.io page.\nMy YouTube channel, which has gotten 2.8K subscribers at the time of writing, is dedicated to Cell Machine content.\nI am currently working on Schemacell - a CMMM mod which will allow for creation of custom cells in Lua language.\nConclusion # On this blog you can expect posts about Cat Bot and Schemacell development, some other nerd stuff, announcements of new projects or miscellaneous topics (e.g. gender).\nMeow meow,\n","date":"April 23nd 2024","externalUrl":null,"permalink":"/posts/hello-world/","section":"Posts","summary":"Hi @everyone!","title":"Hello World","type":"posts"},{"content":"","date":"April 23nd 2024","externalUrl":null,"permalink":"/","section":"Milenakos","summary":"","title":"Milenakos","type":"page"},{"content":"","date":"April 23nd 2024","externalUrl":null,"permalink":"/tags/misc/","section":"Tags","summary":"","title":"Misc","type":"tags"},{"content":"","date":"April 23nd 2024","externalUrl":null,"permalink":"/posts/","section":"Posts","summary":"","title":"Posts","type":"posts"},{"content":"","date":"April 23nd 2024","externalUrl":null,"permalink":"/tags/","section":"Tags","summary":"","title":"Tags","type":"tags"},{"content":"","date":"January 1nd 0001","externalUrl":null,"permalink":"/authors/","section":"Authors","summary":"","title":"Authors","type":"authors"},{"content":"","date":"January 1nd 0001","externalUrl":null,"permalink":"/categories/","section":"Categories","summary":"","title":"Categories","type":"categories"},{"content":"","date":"January 1nd 0001","externalUrl":null,"permalink":"/series/","section":"Series","summary":"","title":"Series","type":"series"}]